[
    {
        "name": "GF0901",
        "description": " Pre-primary  & Primary Education",
        "data": [
            {
                "x": 1995,
                "y": 1726.982404426923
            },
            {
                "x": 1996,
                "y": 1664.8677064283495
            },
            {
                "x": 1997,
                "y": 1638.3413659460855
            },
            {
                "x": 1998,
                "y": 1566.3669979984395
            },
            {
                "x": 1999,
                "y": 1728.341009432069
            },
            {
                "x": 2000,
                "y": 2769.0987422006538
            },
            {
                "x": 2001,
                "y": 2576.2450147530885
            },
            {
                "x": 2002,
                "y": 2617.947138031118
            },
            {
                "x": 2003,
                "y": 3122.740787153068
            },
            {
                "x": 2004,
                "y": 3447.889637399403
            },
            {
                "x": 2005,
                "y": 3583.581791049144
            },
            {
                "x": 2006,
                "y": 3994.818910051557
            },
            {
                "x": 2007,
                "y": 4338.659828442939
            },
            {
                "x": 2008,
                "y": 5817.23053059909
            },
            {
                "x": 2009,
                "y": 6425.682510182292
            },
            {
                "x": 2010,
                "y": 2276.0
            },
            {
                "x": 2011,
                "y": 1121.1643487002
            },
            {
                "x": 2012,
                "y": 2716.3401590008525
            },
            {
                "x": 2013,
                "y": 1566.8650065048237
            },
            {
                "x": 2014,
                "y": 1012.7357973824528
            },
            {
                "x": 2015,
                "y": 994.4473161751436
            },
            {
                "x": 2016,
                "y": 3309.229850711012
            },
            {
                "x": 2017,
                "y": 4287.567655999815
            },
            {
                "x": 2018,
                "y": 4684.721431504037
            },
            {
                "x": 2019,
                "y": 5068.204663993655
            },
            {
                "x": 2020,
                "y": 4949.667476724002
            },
            {
                "x": 2021,
                "y": 4650.176543131798
            }
        ]
    },
    {
        "name": "GF0902",
        "description": " Secondary Education",
        "data": [
            {
                "x": 1995,
                "y": 3491.5381568953667
            },
            {
                "x": 1996,
                "y": 3404.083571995445
            },
            {
                "x": 1997,
                "y": 3373.445611919731
            },
            {
                "x": 1998,
                "y": 3280.233554975065
            },
            {
                "x": 1999,
                "y": 2091.2540136463977
            },
            {
                "x": 2000,
                "y": 1871.0469941566805
            },
            {
                "x": 2001,
                "y": 1594.402483706754
            },
            {
                "x": 2002,
                "y": 3119.567778465052
            },
            {
                "x": 2003,
                "y": 3682.286410470621
            },
            {
                "x": 2004,
                "y": 3881.630210688127
            },
            {
                "x": 2005,
                "y": 4076.704261824992
            },
            {
                "x": 2006,
                "y": 4906.358984191912
            },
            {
                "x": 2007,
                "y": 5313.8435860422505
            },
            {
                "x": 2008,
                "y": 6577.841948350188
            },
            {
                "x": 2009,
                "y": 8606.458737000276
            },
            {
                "x": 2010,
                "y": 10069.0
            },
            {
                "x": 2011,
                "y": 9531.365738207638
            },
            {
                "x": 2012,
                "y": 11677.850303455883
            },
            {
                "x": 2013,
                "y": 14817.68841895972
            },
            {
                "x": 2014,
                "y": 19528.26918322831
            },
            {
                "x": 2015,
                "y": 20621.355845937265
            },
            {
                "x": 2016,
                "y": 21535.897092171777
            },
            {
                "x": 2017,
                "y": 22569.99900215812
            },
            {
                "x": 2018,
                "y": 23440.281887231424
            },
            {
                "x": 2019,
                "y": 25080.608530551614
            },
            {
                "x": 2020,
                "y": 25582.187154805117
            },
            {
                "x": 2021,
                "y": 30636.170946116872
            }
        ]
    },
    {
        "name": "GF0903",
        "description": " Post-Secondary Non-Tertiary Education",
        "data": [
            {
                "x": 1995,
                "y": 3776.8172809143184
            },
            {
                "x": 1996,
                "y": 3623.145112314965
            },
            {
                "x": 1997,
                "y": 3645.176987339592
            },
            {
                "x": 1998,
                "y": 3707.06856192964
            },
            {
                "x": 1999,
                "y": 5276.394742123219
            },
            {
                "x": 2000,
                "y": 6122.502723581262
            },
            {
                "x": 2001,
                "y": 7094.966294867223
            },
            {
                "x": 2002,
                "y": 7858.723366798306
            },
            {
                "x": 2003,
                "y": 8071.743247006406
            },
            {
                "x": 2004,
                "y": 8442.8646351388
            },
            {
                "x": 2005,
                "y": 10674.187546634286
            },
            {
                "x": 2006,
                "y": 9100.099109463546
            },
            {
                "x": 2007,
                "y": 9502.968117591538
            },
            {
                "x": 2008,
                "y": 8064.9612827847395
            },
            {
                "x": 2009,
                "y": 8898.581319941475
            },
            {
                "x": 2010,
                "y": 9472.0
            },
            {
                "x": 2011,
                "y": 8517.91150160964
            },
            {
                "x": 2012,
                "y": 8810.012664894417
            },
            {
                "x": 2013,
                "y": 7595.375757873292
            },
            {
                "x": 2014,
                "y": 6807.524236548716
            },
            {
                "x": 2015,
                "y": 6473.16684113634
            },
            {
                "x": 2016,
                "y": 6330.344935512826
            },
            {
                "x": 2017,
                "y": 5443.835901422504
            },
            {
                "x": 2018,
                "y": 6136.300533734776
            },
            {
                "x": 2019,
                "y": 5506.526586774182
            },
            {
                "x": 2020,
                "y": 2979.191415496292
            },
            {
                "x": 2021,
                "y": 2744.8451808752843
            }
        ]
    },
    {
        "name": "GF0904",
        "description": " Tertiary Education",
        "data": [
            {
                "x": 1995,
                "y": 6273.3575174509015
            },
            {
                "x": 1996,
                "y": 6024.856181636244
            },
            {
                "x": 1997,
                "y": 6056.295874601671
            },
            {
                "x": 1998,
                "y": 6147.990467143875
            },
            {
                "x": 1999,
                "y": 7201.635360224765
            },
            {
                "x": 2000,
                "y": 7601.049024462713
            },
            {
                "x": 2001,
                "y": 8221.52767419993
            },
            {
                "x": 2002,
                "y": 9124.369605557406
            },
            {
                "x": 2003,
                "y": 9544.419706674094
            },
            {
                "x": 2004,
                "y": 9864.698706935527
            },
            {
                "x": 2005,
                "y": 10665.180743515091
            },
            {
                "x": 2006,
                "y": 10280.510716264009
            },
            {
                "x": 2007,
                "y": 10996.184868001
            },
            {
                "x": 2008,
                "y": 12581.091575681883
            },
            {
                "x": 2009,
                "y": 13473.139823638734
            },
            {
                "x": 2010,
                "y": 13418.0
            },
            {
                "x": 2011,
                "y": 11200.87247579178
            },
            {
                "x": 2012,
                "y": 12366.826102221998
            },
            {
                "x": 2013,
                "y": 11388.341319129093
            },
            {
                "x": 2014,
                "y": 12602.312675714978
            },
            {
                "x": 2015,
                "y": 11482.440566003685
            },
            {
                "x": 2016,
                "y": 12319.860100628335
            },
            {
                "x": 2017,
                "y": 12244.836075464693
            },
            {
                "x": 2018,
                "y": 12006.683009443
            },
            {
                "x": 2019,
                "y": 12211.992550565688
            },
            {
                "x": 2020,
                "y": 15444.03115038662
            },
            {
                "x": 2021,
                "y": 13411.942986339487
            }
        ]
    },
    {
        "name": "GF0905",
        "description": " Education not Definable by Level",
        "data": [
            {
                "x": 1995,
                "y": 2834.700368910268
            },
            {
                "x": 1996,
                "y": 2730.967202650012
            },
            {
                "x": 1997,
                "y": 2656.339884592197
            },
            {
                "x": 1998,
                "y": 2668.0451199240088
            },
            {
                "x": 1999,
                "y": 2685.813616295404
            },
            {
                "x": 2000,
                "y": 3278.460483311875
            },
            {
                "x": 2001,
                "y": 2708.488100256153
            },
            {
                "x": 2002,
                "y": 3644.377694247514
            },
            {
                "x": 2003,
                "y": 3775.1471734892793
            },
            {
                "x": 2004,
                "y": 3730.864770774934
            },
            {
                "x": 2005,
                "y": 3072.4457140349086
            },
            {
                "x": 2006,
                "y": 3729.226298521453
            },
            {
                "x": 2007,
                "y": 4120.765538683619
            },
            {
                "x": 2008,
                "y": 3984.942427782926
            },
            {
                "x": 2009,
                "y": 2818.7800624777565
            },
            {
                "x": 2010,
                "y": 2340.0
            },
            {
                "x": 2011,
                "y": 2187.4944585120056
            },
            {
                "x": 2012,
                "y": 1844.988413502533
            },
            {
                "x": 2013,
                "y": 1623.53281867498
            },
            {
                "x": 2014,
                "y": 1678.5676199709162
            },
            {
                "x": 2015,
                "y": 1739.819839006606
            },
            {
                "x": 2016,
                "y": 1663.2492795389048
            },
            {
                "x": 2017,
                "y": 1942.8878008029144
            },
            {
                "x": 2018,
                "y": 2282.68273573286
            },
            {
                "x": 2019,
                "y": 2364.360018763193
            },
            {
                "x": 2020,
                "y": 10503.26886539372
            },
            {
                "x": 2021,
                "y": 13773.70449658487
            }
        ]
    },
    {
        "name": "GF0906",
        "description": " Subsidiary Services to Education",
        "data": [
            {
                "x": 1995,
                "y": 189.2583456906217
            },
            {
                "x": 1996,
                "y": 189.8533349435837
            },
            {
                "x": 1997,
                "y": 188.22368443717164
            },
            {
                "x": 1998,
                "y": 182.7428164331513
            },
            {
                "x": 1999,
                "y": 184.030353200883
            },
            {
                "x": 2000,
                "y": 250.2350698227196
            },
            {
                "x": 2001,
                "y": 266.98132356278984
            },
            {
                "x": 2002,
                "y": 519.9279630775087
            },
            {
                "x": 2003,
                "y": 594.070778798849
            },
            {
                "x": 2004,
                "y": 555.5126593724568
            },
            {
                "x": 2005,
                "y": 730.6769030445788
            },
            {
                "x": 2006,
                "y": 689.6664110102688
            },
            {
                "x": 2007,
                "y": 483.85349637731446
            },
            {
                "x": 2008,
                "y": 881.5238306272914
            },
            {
                "x": 2009,
                "y": 1359.1814622958595
            },
            {
                "x": 2010,
                "y": 1433.0
            },
            {
                "x": 2011,
                "y": 951.765717848554
            },
            {
                "x": 2012,
                "y": 599.2352535486783
            },
            {
                "x": 2013,
                "y": 642.2352045951055
            },
            {
                "x": 2014,
                "y": 711.5261633543383
            },
            {
                "x": 2015,
                "y": 707.4094502400462
            },
            {
                "x": 2016,
                "y": 762.5498063022629
            },
            {
                "x": 2017,
                "y": 828.584503283596
            },
            {
                "x": 2018,
                "y": 991.7076091419189
            },
            {
                "x": 2019,
                "y": 924.7733115918558
            },
            {
                "x": 2020,
                "y": 1245.9172794697806
            },
            {
                "x": 2021,
                "y": 1286.443397419681
            }
        ]
    },
    {
        "name": "GF0907",
        "description": " Research and Development Education",
        "data": [
            {
                "x": 1995,
                "y": 87.67114543021447
            },
            {
                "x": 1996,
                "y": 80.98638763327696
            },
            {
                "x": 1997,
                "y": 80.85665317371458
            },
            {
                "x": 1998,
                "y": 80.92896156325271
            },
            {
                "x": 1999,
                "y": 83.65016054585591
            },
            {
                "x": 2000,
                "y": 88.91601465781916
            },
            {
                "x": 2001,
                "y": 129.74793294640253
            },
            {
                "x": 2002,
                "y": 119.60784127135176
            },
            {
                "x": 2003,
                "y": 83.33658219623133
            },
            {
                "x": 2004,
                "y": 81.18139072248847
            },
            {
                "x": 2005,
                "y": 74.306125733347
            },
            {
                "x": 2006,
                "y": 85.25194938003322
            },
            {
                "x": 2007,
                "y": 79.04008550092996
            },
            {
                "x": 2008,
                "y": 35.13694049393659
            },
            {
                "x": 2009,
                "y": 25.357863102534694
            },
            {
                "x": 2010,
                "y": 16.0
            },
            {
                "x": 2011,
                "y": 8.81264553563476
            },
            {
                "x": 2012,
                "y": 14.47428148668305
            },
            {
                "x": 2013,
                "y": 17.944807187216185
            },
            {
                "x": 2014,
                "y": 16.78567619970916
            },
            {
                "x": 2015,
                "y": 1104.6328195502292
            },
            {
                "x": 2016,
                "y": 362.6428757027449
            },
            {
                "x": 2017,
                "y": 1562.5246559766088
            },
            {
                "x": 2018,
                "y": 1719.2523949637337
            },
            {
                "x": 2019,
                "y": 1956.1190122519176
            },
            {
                "x": 2020,
                "y": 2057.9088527694494
            },
            {
                "x": 2021,
                "y": 2038.3557740956237
            }
        ]
    },
    {
        "name": "GF0908",
        "description": " Education not elsewhere classified",
        "data": [
            {
                "x": 1995,
                "y": 24340.571503490177
            },
            {
                "x": 1996,
                "y": 23321.424346985958
            },
            {
                "x": 1997,
                "y": 23420.593523383
            },
            {
                "x": 1998,
                "y": 23269.687061098484
            },
            {
                "x": 1999,
                "y": 24423.273028296207
            },
            {
                "x": 2000,
                "y": 25841.5343171239
            },
            {
                "x": 2001,
                "y": 29361.707710515228
            },
            {
                "x": 2002,
                "y": 32805.501689108816
            },
            {
                "x": 2003,
                "y": 35450.191543674
            },
            {
                "x": 2004,
                "y": 37017.554435301565
            },
            {
                "x": 2005,
                "y": 37839.83160451201
            },
            {
                "x": 2006,
                "y": 40347.12450466573
            },
            {
                "x": 2007,
                "y": 40411.91398550926
            },
            {
                "x": 2008,
                "y": 41428.51972120383
            },
            {
                "x": 2009,
                "y": 39910.23357981731
            },
            {
                "x": 2010,
                "y": 44206.0
            },
            {
                "x": 2011,
                "y": 44027.97709603126
            },
            {
                "x": 2012,
                "y": 39487.76979986959
            },
            {
                "x": 2013,
                "y": 37672.76153071995
            },
            {
                "x": 2014,
                "y": 37066.50319922443
            },
            {
                "x": 2015,
                "y": 35942.69638667293
            },
            {
                "x": 2016,
                "y": 32447.903021212263
            },
            {
                "x": 2017,
                "y": 29954.936961919568
            },
            {
                "x": 2018,
                "y": 28473.417407964967
            },
            {
                "x": 2019,
                "y": 27749.21553100952
            },
            {
                "x": 2020,
                "y": 20839.76777655042
            },
            {
                "x": 2021,
                "y": 18969.76780293448
            }
        ]
    }
]